Metadata-Version: 1.0
Name: sec1
Version: 1.0.0
Summary: sec
Home-page: UNKNOWN
Author: UNKNOWN
Author-email: 123312223@gmail.com
License: UNKNOWN
Platform: UNKNOWN
